MANIFEST.in
README.md
VERSION
setup.cfg
setup.py
aiosqlalchemy_miniorm/__init__.py
aiosqlalchemy_miniorm/orm.py
aiosqlalchemy_miniorm.egg-info/PKG-INFO
aiosqlalchemy_miniorm.egg-info/SOURCES.txt
aiosqlalchemy_miniorm.egg-info/dependency_links.txt
aiosqlalchemy_miniorm.egg-info/requires.txt
aiosqlalchemy_miniorm.egg-info/top_level.txt