Metadata-Version: 1.1
Name: aiosqlalchemy-miniorm
Version: 0.2.13
Summary: UNKNOWN
Home-page: UNKNOWN
Author: Wargaming Team
Author-email: UNKNOWN
License: UNKNOWN
Platform: UNKNOWN
Classifier: Programming Language :: Python
Classifier: Programming Language :: Python :: 3.5
Classifier: Programming Language :: Python :: 3.6
